cecode/__init__.py
cecode/py.typed
cecode/eurocode_7_1/__init__.py
cecode/eurocode_7_1/cl6_5_bearing_resistance_zeroshot.py
cecode/eurocode_7_1/clause_6_5_bearing_resistance.py
cecode/eurocode_7_1/mo_new_clause_6_5_bearing_resistance.txt
cecode/eurocode_7_2/__init__.py
cecode-0.1.0.dist-info/METADATA
cecode-0.1.0.dist-info/WHEEL
cecode-0.1.0.dist-info/licenses/LICENSE
cecode-0.1.0.dist-info/RECORD
