Metadata-Version: 2.4
Name: cecode
Version: 0.1.0
Summary: Civil Engineering Codes in readable, usable, executable Python.
Project-URL: Source, https://github.com/bedrock-engineer/cecode
Project-URL: Tracker, https://github.com/bedrock-engineer/cecode/issues
Author-email: Bedrock <info@bedrock.engineer>
License-File: LICENSE
Keywords: aec,bim,british-standard,bsi,civil-engineering,eurocode,geotechnical-engineering,ground-engineering,structural-engineering
Requires-Python: >=3.9
Requires-Dist: marimo>=0.12.10
Requires-Dist: matplotlib>=3.9.4
Requires-Dist: numpy>=2.0.2
